mineshaft.py
mineshaft-0.0.1.dist-info/DESCRIPTION.rst
mineshaft-0.0.1.dist-info/METADATA
mineshaft-0.0.1.dist-info/metadata.json
mineshaft-0.0.1.dist-info/RECORD
mineshaft-0.0.1.dist-info/top_level.txt
mineshaft-0.0.1.dist-info/WHEEL
mineshaft-0.0.1.dist-info/zip-safe
